VLSI Design/Resources/Verilog Resources/Verilog Session/Codes/fullAdder/fullAdder.v
module fullAdder(a,b,c_in,sum,c_out,done);

    input a,b,c_in;
    output reg sum,c_out,done;

    always @ (*)
    begin
        done = 0;
        c_out = (a&b)|(a&c_in)|(b&c_in);
        sum = a^b^c_in;
        done = 1;
    end

endmodule

VLSI Design/Resources/Verilog Resources/Verilog Session/Codes/fullAdder/fullAdderTest.v
module test();

    reg a,b,c_in;
    wire c_out,sum,done;

    fullAdder uut(.a(a),.b(b),.c_in(c_in),.sum(sum),.c_out(c_out),.done(done));

    initial begin
		$dumpfile("fullAdder.vcd");
     	$dumpvars(0,test);
		// Initialize Inputs
		a = 1'b0;
		b = 1'b0;
        c_in = 1'b0;

		#80 $finish;//global reset
	end

	always #10 a=~a;
	always #20 b=~b;
    always #40 c_in=~c_in;

	always @(posedge done)
    $display("time =%0t , a = %b , b = %b , c_in = %b , sum = %b , c_out = %b",$time,a,b,c_in,sum,c_out);

endmodule

VLSI Design/Resources/Verilog Resources/Verilog Session/Codes/fullAdder/fullAdder.vcd
$date
	Fri Aug 20 22:58:22 2021
$end
$version
	Icarus Verilog
$end
$timescale
	1s
$end
$scope module test $end
$var wire 1 ! sum $end
$var wire 1 " done $end
$var wire 1 # c_out $end
$var reg 1 $ a $end
$var reg 1 % b $end
$var reg 1 & c_in $end
$scope module uut $end
$var wire 1 $ a $end
$var wire 1 % b $end
$var wire 1 & c_in $end
$var reg 1 # c_out $end
$var reg 1 " done $end
$var reg 1 ! sum $end
$upscope $end
$upscope $end
$enddefinitions $end
#0
$dumpvars
0&
0%
0$
0#
1"
0!
$end
#10
1!
1"
1$
#20
1"
0$
1%
#30
0!
1#
1"
1$
#40
1!
0#
1"
0$
0%
1&
#50
0!
1#
1"
1$
#60
1"
0$
1%
#70
1!
1"
1$
#80
0!
0#
1"
0$
0%
0&
