VLSI Design/Resources/Verilog Resources/Verilog Session/Codes/halfAdder/halfAdder.v
`timescale 1ns / 1ps
module halfAdder(a,b,s,carry,done);

    input a,b;
    output reg carry,s,done;

    always @ (*)
    begin
        done = 0;
        carry = a&b;
        s = a^b;
        done = 1;
    end

endmodule

VLSI Design/Resources/Verilog Resources/Verilog Session/Codes/halfAdder/halfAdderTest.v
module test();

    reg a,b;
    wire carry,s,done;

    halfAdder uut(.a(a),.b(b),.s(s),.carry(carry),.done(done));

    initial begin
		$dumpfile("halfAdder.vcd");
     	$dumpvars(0,test);
		// Initialize Inputs
		a = 1'b0;
		b = 1'b0;

		#70 $finish;//global reset
	end

	always #10 a=~a;
	always #20 b=~b;

	always @(posedge done)
    $display( "time =%0t , a = %b , b = %b , s = %b , carry = %b",$time,a,b,s,carry);

endmodule

VLSI Design/Resources/Verilog Resources/Verilog Session/Codes/halfAdder/halfAdder.vcd
$date
	Fri Aug 20 22:41:49 2021
$end
$version
	Icarus Verilog
$end
$timescale
	1ps
$end
$scope module test $end
$var wire 1 ! s $end
$var wire 1 " done $end
$var wire 1 # carry $end
$var reg 1 $ a $end
$var reg 1 % b $end
$scope module uut $end
$var wire 1 $ a $end
$var wire 1 % b $end
$var reg 1 # carry $end
$var reg 1 " done $end
$var reg 1 ! s $end
$upscope $end
$upscope $end
$enddefinitions $end
#0
$dumpvars
0%
0$
0#
1"
0!
$end
#10000000000000
1!
1"
1$
#20000000000000
1"
0$
1%
#30000000000000
0!
1#
1"
1$
#40000000000000
0#
1"
0$
0%
#50000000000000
1!
1"
1$
#60000000000000
1"
0$
1%
#70000000000000
0!
1#
1"
1$
