VLSI Design/Resources/Verilog Resources/Verilog Session/Codes/DFlipFlop/DFF.v
module DFF(D,Clk,Q,done);

    input D,Clk;
    output reg Q,done;

    always @ (posedge Clk)
    begin
        done=0;
        Q=D;
        done=1;
    end

endmodule

VLSI Design/Resources/Verilog Resources/Verilog Session/Codes/DFlipFlop/DFFTest.v
module test();

    reg D,Clk;
    wire Q,done;

    DFF uut(.D(D),.Clk(Clk),.Q(Q),.done(done));

    initial begin
		$dumpfile("DFFTest.vcd");
     	$dumpvars(0,test);
		// Initialize Inputs
		D = 1'b0;
        Clk = 1'b0;

		#80 $finish;//global reset
	end

	always #10 D=~D;
	always #15 Clk=~Clk;

	always @(Clk)
    begin
        #1;
        $display("time =%0t , D = %b , Clk = %b , Q = %b",$time,D,Clk,Q);
    end

endmodule

VLSI Design/Resources/Verilog Resources/Verilog Session/Codes/DFlipFlop/DFFTest.vcd
$date
	Sat Aug 21 00:48:09 2021
$end
$version
	Icarus Verilog
$end
$timescale
	1s
$end
$scope module test $end
$var wire 1 ! done $end
$var wire 1 " Q $end
$var reg 1 # Clk $end
$var reg 1 $ D $end
$scope module uut $end
$var wire 1 # Clk $end
$var wire 1 $ D $end
$var reg 1 " Q $end
$var reg 1 ! done $end
$upscope $end
$upscope $end
$enddefinitions $end
#0
$dumpvars
0$
0#
x"
x!
$end
#10
1$
#15
1"
1!
1#
#20
0$
#30
1$
0#
#40
0$
#45
0"
1!
1#
#50
1$
#60
0$
0#
#70
1$
#75
1"
1!
1#
#80
0$
